Metadata-Version: 1.1
Name: hellopackage-asliddin750750
Version: 0.0.1
Summary: Hello package
Home-page: UNKNOWN
Author: NeuralNine (Florian Dedov)
Author-email: <mail@neuralnine.com>
License: UNKNOWN
Keywords: python,video,stream,video stream,camera stream,sockets
Platform: UNKNOWN
Classifier: Development Status :: 1 - Planning
Classifier: Intended Audience :: Developers
Classifier: Programming Language :: Python :: 3
Classifier: Operating System :: Unix
Classifier: Operating System :: MacOS :: MacOS X
Classifier: Operating System :: Microsoft :: Windows
